iso8583_dlib/__init__.py
iso8583_dlib/parser.py
iso8583_dlib/segments/__init__.py
iso8583_dlib/segments/data_elements.py
iso8583_dlib/segments/header.py
iso8583_dlib/segments/iso.py
iso8583_dlib/segments/mti.py
iso8583_dlib/segments/primary_bitmap.py
iso8583_dlib/segments/data/__init__.py
iso8583_dlib/segments/data/data_elements/__init__.py
iso8583_dlib/segments/data/data_elements/list_elements.py
iso8583_dlib/segments/data/header/__init__.py
iso8583_dlib/segments/data/header/header_OC.py
iso8583_dlib/segments/data/header/header_PI.py
iso8583_dlib/segments/data/header/header_RC.py
iso8583_dlib/segments/data/header/header_RN.py
iso8583_dlib/segments/data/header/header_Status.py
iso8583_dlib/segments/data/mti/__init__.py
iso8583_dlib/segments/data/mti/mti_types.py
iso8583_dlib/segments/utilities/__init__.py
iso8583_dlib/segments/utilities/operations.py
ISO8583_Dlib-0.1.8.dist-info/AUTHORS.md
ISO8583_Dlib-0.1.8.dist-info/LICENSE
ISO8583_Dlib-0.1.8.dist-info/METADATA
ISO8583_Dlib-0.1.8.dist-info/WHEEL
ISO8583_Dlib-0.1.8.dist-info/top_level.txt
ISO8583_Dlib-0.1.8.dist-info/RECORD
