Metadata-Version: 2.1
Name: ISO8583-Dlib
Version: 0.1.8
Summary: Parser String to JSON for ISO8583 Package
Home-page: UNKNOWN
Author: eocode
Author-email: hola@eliasojedamedina.com
License: MIT license
Project-URL: Homepage, https://github.com/eocode/ISO8583-Dlib
Project-URL: Issue tracker, https://github.com/eocode/ISO8583-Dlib/issues
Project-URL: Code, https://github.com/eocode/ISO8583-Dlib
Project-URL: Documentation, https://github.com/eocode/ISO8583-Dlib/wiki
Platform: UNKNOWN
Classifier: Programming Language :: Python :: 3
Classifier: Operating System :: OS Independent
Requires-Python: >=3.6
